pgs_compare/__init__.py
pgs_compare/analyze.py
pgs_compare/calculate.py
pgs_compare/cli.py
pgs_compare/compare.py
pgs_compare/download.py
pgs_compare/visualize.py
pgs_compare/scripts/download_1000_genomes.sh
pgs_compare/scripts/download_reference.sh
pgs_compare-0.2.4.dist-info/licenses/LICENSE
tests/__init__.py
tests/test_init.py
pgs_compare-0.2.4.dist-info/METADATA
pgs_compare-0.2.4.dist-info/WHEEL
pgs_compare-0.2.4.dist-info/entry_points.txt
pgs_compare-0.2.4.dist-info/top_level.txt
pgs_compare-0.2.4.dist-info/RECORD
