Metadata-Version: 2.4
Name: pgs_compare
Version: 0.2.4
Summary: Compare PGS across ancestry groups
Home-page: https://github.com/alex1craig/pgs-compare
Author: Alexander Craig
Classifier: Programming Language :: Python :: 3
Classifier: License :: OSI Approved :: MIT License
Classifier: Operating System :: POSIX :: Linux
Requires-Python: >=3.8
License-File: LICENSE
Requires-Dist: pandas
Requires-Dist: numpy
Requires-Dist: matplotlib
Requires-Dist: requests
Requires-Dist: zstandard
Requires-Dist: pgscatalog-utils
Requires-Dist: scipy
Dynamic: author
Dynamic: classifier
Dynamic: description
Dynamic: description-content-type
Dynamic: home-page
Dynamic: license-file
Dynamic: requires-dist
Dynamic: requires-python
Dynamic: summary
